CGMissingData/__init__.py
CGMissingData/runner.py
cgmissingdata-0.1.2.dist-info/METADATA
cgmissingdata-0.1.2.dist-info/WHEEL
cgmissingdata-0.1.2.dist-info/top_level.txt
cgmissingdata-0.1.2.dist-info/RECORD
