Metadata-Version: 2.4
Name: CGMissingData
Version: 0.1.2
Summary: MICE + Random Forest + KNN to handle missing values of CGM device
Author: HS Shad
Requires-Python: >=3.9
Requires-Dist: numpy>=1.23
Requires-Dist: pandas>=1.5
Requires-Dist: scikit-learn>=1.2
